winsdk/_winrt.pyd
winsdk/_winrt.pyi
winsdk/py.typed
winsdk/system/__init__.py
winsdk/windows/ai/machinelearning/__init__.py
winsdk/windows/ai/machinelearning/__init__.pyi
winsdk/windows/ai/machinelearning/preview/__init__.py
winsdk/windows/ai/machinelearning/preview/__init__.pyi
winsdk/windows/applicationmodel/__init__.py
winsdk/windows/applicationmodel/__init__.pyi
winsdk/windows/applicationmodel/activation/__init__.py
winsdk/windows/applicationmodel/activation/__init__.pyi
winsdk/windows/applicationmodel/appextensions/__init__.py
winsdk/windows/applicationmodel/appextensions/__init__.pyi
winsdk/windows/applicationmodel/appointments/__init__.py
winsdk/windows/applicationmodel/appointments/__init__.pyi
winsdk/windows/applicationmodel/appointments/appointmentsprovider/__init__.py
winsdk/windows/applicationmodel/appointments/appointmentsprovider/__init__.pyi
winsdk/windows/applicationmodel/appointments/dataprovider/__init__.py
winsdk/windows/applicationmodel/appointments/dataprovider/__init__.pyi
winsdk/windows/applicationmodel/appservice/__init__.py
winsdk/windows/applicationmodel/appservice/__init__.pyi
winsdk/windows/applicationmodel/background/__init__.py
winsdk/windows/applicationmodel/background/__init__.pyi
winsdk/windows/applicationmodel/calls/__init__.py
winsdk/windows/applicationmodel/calls/__init__.pyi
winsdk/windows/applicationmodel/calls/background/__init__.py
winsdk/windows/applicationmodel/calls/background/__init__.pyi
winsdk/windows/applicationmodel/calls/provider/__init__.py
winsdk/windows/applicationmodel/calls/provider/__init__.pyi
winsdk/windows/applicationmodel/chat/__init__.py
winsdk/windows/applicationmodel/chat/__init__.pyi
winsdk/windows/applicationmodel/communicationblocking/__init__.py
winsdk/windows/applicationmodel/communicationblocking/__init__.pyi
winsdk/windows/applicationmodel/contacts/__init__.py
winsdk/windows/applicationmodel/contacts/__init__.pyi
winsdk/windows/applicationmodel/contacts/dataprovider/__init__.py
winsdk-1.0.0b9.dist-info/LICENSE
winsdk-1.0.0b9.dist-info/METADATA
winsdk-1.0.0b9.dist-info/WHEEL
winsdk-1.0.0b9.dist-info/top_level.txt
winsdk-1.0.0b9.dist-info/RECORD
